sturmer/__init__.py
sturmer/api.py
sturmer/search.py
sturmer/storage.py
sturmer/data/__init__.py
sturmer/data/tasks.py
sturmer-0.1.2.dist-info/METADATA
sturmer-0.1.2.dist-info/WHEEL
sturmer-0.1.2.dist-info/top_level.txt
sturmer-0.1.2.dist-info/RECORD
