Metadata-Version: 2.4
Name: sturmer
Version: 0.1.2
Author: Sturmer
Classifier: Programming Language :: Python :: 3
Classifier: Programming Language :: Python :: 3 :: Only
Classifier: Operating System :: OS Independent
Requires-Python: >=3.9
Provides-Extra: dev
Requires-Dist: pytest>=7.4; extra == "dev"
Requires-Dist: flake8>=6.1; extra == "dev"
